xengine_commons/__init__.py
xengine_commons/api/__init__.py
xengine_commons/api/response.py
xengine_commons/api/status.py
xengine_commons-0.0.7.dist-info/licenses/LICENSE
xengine_commons-0.0.7.dist-info/METADATA
xengine_commons-0.0.7.dist-info/WHEEL
xengine_commons-0.0.7.dist-info/top_level.txt
xengine_commons-0.0.7.dist-info/RECORD
