Metadata-Version: 2.4
Name: xengine-commons
Version: 0.0.7
Summary: Xengine Commons 是 Fengyun AI 团队维护的基础工具库
Author-email: lhybdv <39660787@qq.com>
License: Apache Software License
Project-URL: Homepage, https://github.com/windcloudai/xengine-commons
Classifier: Programming Language :: Python :: 3
Classifier: License :: OSI Approved :: Apache Software License
Requires-Python: >=3.8
License-File: LICENSE
Requires-Dist: utype>=0.6.5
Dynamic: license-file
